astrocache/__init__.py
astrocache-0.0.4.dist-info/LICENSE
astrocache-0.0.4.dist-info/WHEEL
astrocache-0.0.4.dist-info/METADATA
astrocache-0.0.4.dist-info/RECORD
