Metadata-Version: 2.1
Name: astrocache
Version: 0.0.4
Summary: Durable memoization that refreshes on code updates
Author-email: Andrew Matteson <andrewkmatteson@gmail.com>
Requires-Python: >=3.9
Classifier: Programming Language :: Python :: 3
Classifier: License :: OSI Approved :: MIT License
Classifier: Operating System :: OS Independent
Project-URL: Homepage, https://github.com/aromatt/astrocache
Project-URL: Issues, https://github.com/aromatt/astrocache/issues
